MysqlOperater_zhaozl/__init__.py
MysqlOperater_zhaozl/__version__.py
MysqlOperater_zhaozl/core.py
MysqlOperater_zhaozl-1.1.dist-info/LICENSE
MysqlOperater_zhaozl-1.1.dist-info/METADATA
MysqlOperater_zhaozl-1.1.dist-info/WHEEL
MysqlOperater_zhaozl-1.1.dist-info/top_level.txt
MysqlOperater_zhaozl-1.1.dist-info/RECORD
