Metadata-Version: 2.1
Name: MysqlOperater-zhaozl
Version: 1.1
Summary: MysqlOperater_zhaozl.
Home-page: https://github.com/me/MysqlOperater_zhaozl
Author: zhaozl
Author-email: 545362989@qq.com
License: MIT
Platform: UNKNOWN
Classifier: License :: OSI Approved :: MIT License
Classifier: Programming Language :: Python
Classifier: Programming Language :: Python :: 3
Classifier: Programming Language :: Python :: 3.6
Classifier: Programming Language :: Python :: Implementation :: CPython
Classifier: Programming Language :: Python :: Implementation :: PyPy
Requires-Python: >=3.7.0
